fleetmonger/__init__.py
fleetmonger/fleetmonger.py
fleetmonger/port.py
fleetmonger/utils.py
fleetmonger/vessel.py
fleetmonger/vessel_wrapper.py
fleetmonger/weather.py
fleetmonger-0.0.4.dist-info/DESCRIPTION.rst
fleetmonger-0.0.4.dist-info/METADATA
fleetmonger-0.0.4.dist-info/RECORD
fleetmonger-0.0.4.dist-info/WHEEL
fleetmonger-0.0.4.dist-info/metadata.json
fleetmonger-0.0.4.dist-info/top_level.txt
