Metadata-Version: 2.0
Name: fleetmonger
Version: 0.0.4
Summary: Fleetmon API wrapper for ship data
Home-page: https://github.com/fitnr/fleetmonger
Author: Neil Freeman
Author-email: contact@fakeisthenewreal.org
License: MIT
Platform: UNKNOWN
Classifier: License :: OSI Approved :: MIT License
Classifier: Programming Language :: Python :: 2.7
Classifier: Intended Audience :: Science/Research
Requires-Dist: pytz (==2014.10)
Requires-Dist: requests (>=2.4.1,<3)
